setup.py
client/__init__.py
client/client.py
client/client/__init__.py
client/client/add_contact.py
client/client/database.py
client/client/del_contact.py
client/client/main_window.py
client/client/main_window_conv.py
client/client/start_dialog.py
client/client/transport.py
client/common/__init__.py
client/common/decorators.py
client/common/descryptors.py
client/common/errors.py
client/common/metaclasses.py
client/common/settings.py
client/common/utils.py
client/logs/__init__.py
client/logs/client_log_config.py
client/logs/server_log_config.py
client/tests/__init__.py
lite_messenger_client.egg-info/PKG-INFO
lite_messenger_client.egg-info/SOURCES.txt
lite_messenger_client.egg-info/dependency_links.txt
lite_messenger_client.egg-info/requires.txt
lite_messenger_client.egg-info/top_level.txt